README.md
setup.py
auto_regex/__init__.py
auto_regex.egg-info/PKG-INFO
auto_regex.egg-info/SOURCES.txt
auto_regex.egg-info/dependency_links.txt
auto_regex.egg-info/top_level.txt