Metadata-Version: 1.0
Name: auto-regex
Version: 0.3.2
Summary: regex made easy
Home-page: https://github.com/HelloChatterbox/auto_regex
Author: jarbasAI
Author-email: jarbasai@mailfence.com
License: MIT
Platform: UNKNOWN
